morgana_engine/__init__.py
morgana_engine/engine.py
morgana_engine/adapters/__init__.py
morgana_engine/adapters/repository/__init__.py
morgana_engine/adapters/repository/connection.py
morgana_engine/adapters/repository/dataio.py
morgana_engine/models/__init__.py
morgana_engine/models/parsedsql.py
morgana_engine/models/readingfilter.py
morgana_engine/models/schema.py
morgana_engine/models/sql.py
morgana_engine/services/__init__.py
morgana_engine/services/interpreters/__init__.py
morgana_engine/services/interpreters/lex.py
morgana_engine/services/interpreters/parse.py
morgana_engine/services/interpreters/parsers/__init__.py
morgana_engine/services/interpreters/parsers/select.py
morgana_engine/utils/__init__.py
morgana_engine/utils/sql.py
morgana_engine/utils/types.py
morgana_engine/utils/uri.py
tests/__init__.py
tests/morgana_engine/__init__.py
tests/morgana_engine/adapters/__init__.py
tests/morgana_engine/adapters/repository/__init__.py
tests/morgana_engine/adapters/repository/test_connection.py
tests/morgana_engine/adapters/repository/test_dataio.py
tests/morgana_engine/models/__init__.py
tests/morgana_engine/models/test_readingfilter.py
tests/morgana_engine/models/test_schema.py
tests/morgana_engine/services/__init__.py
tests/morgana_engine/services/interpreters/__init__.py
tests/morgana_engine/services/interpreters/test_lex.py
tests/morgana_engine/services/interpreters/test_parse.py
tests/morgana_engine/services/interpreters/parsers/__init__.py
tests/morgana_engine/services/interpreters/parsers/test_select.py
morgana_engine-0.4.0.dist-info/LICENSE
morgana_engine-0.4.0.dist-info/METADATA
morgana_engine-0.4.0.dist-info/WHEEL
morgana_engine-0.4.0.dist-info/top_level.txt
morgana_engine-0.4.0.dist-info/RECORD
