Metadata-Version: 2.1
Name: morgana_engine
Version: 0.4.0
Summary: Python module for handling partitioned data using SQL queries.
Home-page: https://github.com/rjmalves/morgana_engine
Author: Rogerio Alves
Author-email: rogerioalves.ee@gmail.com
Classifier: Programming Language :: Python :: 3
Classifier: License :: OSI Approved :: MIT License
Classifier: Operating System :: OS Independent
Classifier: Development Status :: 3 - Alpha
Requires-Python: >=3.10
License-File: LICENSE
Requires-Dist: numpy
Requires-Dist: pandas
Requires-Dist: python-dotenv
Requires-Dist: pyarrow
Requires-Dist: boto3
Requires-Dist: s3fs >=2023.10.0
